spatial_efd/__init__.py
spatial_efd/spatial_efd.py
spatial_efd-1.2.1.dist-info/LICENCE.txt
spatial_efd-1.2.1.dist-info/METADATA
spatial_efd-1.2.1.dist-info/WHEEL
spatial_efd-1.2.1.dist-info/top_level.txt
spatial_efd-1.2.1.dist-info/RECORD
