Metadata-Version: 2.1
Name: spatial-efd
Version: 1.2.1
Summary: Spatial elliptical fourier analysis
Home-page: http://github.com/sgrieve/spatial_efd
Author: Stuart WD Grieve
Author-email: stuart@swdg.io
License: MIT
Keywords: GIS elliptical fourier analysis shapefile
Platform: UNKNOWN
Classifier: Development Status :: 5 - Production/Stable
Classifier: License :: OSI Approved :: MIT License
Classifier: Programming Language :: Python :: 2.7
Classifier: Programming Language :: Python :: 3
Classifier: Intended Audience :: Science/Research
Classifier: Topic :: Scientific/Engineering :: GIS
Classifier: Operating System :: OS Independent
Requires-Dist: matplotlib (>=2.0.0)
Requires-Dist: numpy (>=1.12.0)
Requires-Dist: pyshp (>=1.2.10)
Requires-Dist: future
